welleng/__init__.py
welleng/clearance.py
welleng/import_data.py
welleng/well_data.py
welleng/well_utils.py
welleng-0.1.0.dist-info/LICENSE
welleng-0.1.0.dist-info/METADATA
welleng-0.1.0.dist-info/WHEEL
welleng-0.1.0.dist-info/top_level.txt
welleng-0.1.0.dist-info/RECORD
