Metadata-Version: 2.1
Name: welleng
Version: 0.1.0
Summary: A collection of Well Engineering modules
Home-page: https://github.com/jonnymaserati/welleng
Author: Jonathan Corcutt
Author-email: jonnycorcutt@gmail.com
License: MIT License
Platform: UNKNOWN
Classifier: License :: OSI Approved :: MIT License
Classifier: Operating System :: OS Independent
Classifier: Programming Language :: Python :: 3
Requires-Python: >=3.8
Requires-Dist: pandas
Requires-Dist: numpy
